coredumpy/__init__.py
coredumpy/__main__.py
coredumpy/conf_hook.py
coredumpy/config.py
coredumpy/coredumpy.py
coredumpy/dap_server.py
coredumpy/except_hook.py
coredumpy/main.py
coredumpy/patch.py
coredumpy/py_object_container.py
coredumpy/py_object_proxy.py
coredumpy/pytest_hook.py
coredumpy/type_support.py
coredumpy/unittest_hook.py
coredumpy/utils.py
coredumpy/types/__init__.py
coredumpy/types/builtin_types.py
coredumpy/types/stdlib_types.py
coredumpy/types/torch_types.py
coredumpy-0.5.0.dist-info/licenses/LICENSE
coredumpy-0.5.0.dist-info/licenses/NOTICE.txt
coredumpy-0.5.0.dist-info/METADATA
coredumpy-0.5.0.dist-info/WHEEL
coredumpy-0.5.0.dist-info/entry_points.txt
coredumpy-0.5.0.dist-info/top_level.txt
coredumpy-0.5.0.dist-info/RECORD
