Metadata-Version: 2.4
Name: coredumpy
Version: 0.5.0
Summary: coredumpy saves your crash site for post-mortem debugging
Author-email: Tian Gao <gaogaotiantian@hotmail.com>
License-Expression: Apache-2.0
Project-URL: Homepage, https://github.com/gaogaotiantian/coredumpy
Classifier: Development Status :: 4 - Beta
Classifier: Programming Language :: Python :: 3.10
Classifier: Programming Language :: Python :: 3.11
Classifier: Programming Language :: Python :: 3.12
Classifier: Programming Language :: Python :: 3.13
Classifier: Programming Language :: Python :: 3.14
Classifier: Intended Audience :: Developers
Classifier: Operating System :: MacOS
Classifier: Operating System :: POSIX :: Linux
Classifier: Operating System :: Microsoft :: Windows
Classifier: Topic :: Software Development :: Quality Assurance
Classifier: Topic :: Software Development :: Bug Tracking
Classifier: Topic :: System :: Logging
Requires-Python: >=3.10
License-File: LICENSE
License-File: NOTICE.txt
Dynamic: license-file
